LLM_function_calling_interface/__init__.py
LLM_function_calling_interface/Controller/CompletionsController.py
LLM_function_calling_interface/Controller/__init__.py
LLM_function_calling_interface/Model/Completions.py
LLM_function_calling_interface/Model/FunctionCall.py
LLM_function_calling_interface/Model/FunctionResponse.py
LLM_function_calling_interface/Model/Messages.py
LLM_function_calling_interface/Model/ParameterProperties.py
LLM_function_calling_interface/Model/Tool.py
LLM_function_calling_interface/Model/ToolDetail.py
LLM_function_calling_interface/Model/ToolParameter.py
LLM_function_calling_interface/Model/__init__.py
LLM_function_calling_interface-1.0.7.dist-info/METADATA
LLM_function_calling_interface-1.0.7.dist-info/WHEEL
LLM_function_calling_interface-1.0.7.dist-info/top_level.txt
LLM_function_calling_interface-1.0.7.dist-info/RECORD
